winzy_screenshot/__init__.py
winzy_screenshot-0.0.4.dist-info/LICENSE
winzy_screenshot-0.0.4.dist-info/METADATA
winzy_screenshot-0.0.4.dist-info/WHEEL
winzy_screenshot-0.0.4.dist-info/entry_points.txt
winzy_screenshot-0.0.4.dist-info/top_level.txt
winzy_screenshot-0.0.4.dist-info/RECORD
