Metadata-Version: 2.1
Name: winzy-screenshot
Version: 0.0.4
Summary: Screenshot using python 
Author: Sukhbinder Singh
License: Apache-2.0
Project-URL: Homepage, https://github.com/sukhbinder/winzy-screenshot
Project-URL: Changelog, https://github.com/sukhbinder/winzy-screenshot/releases
Project-URL: Issues, https://github.com/sukhbinder/winzy-screenshot/issues
Project-URL: CI, https://github.com/sukhbinder/winzy-screenshot/actions
Classifier: License :: OSI Approved :: Apache Software License
License-File: LICENSE
Requires-Dist: winzy
Requires-Dist: pynput
Requires-Dist: pillow
Requires-Dist: winzy-win-geometry
Provides-Extra: test
Requires-Dist: pytest; extra == "test"
